blep/__init__.py
blep/core.py
blep/pipelines.py
blep-0.0.1.dist-info/LICENSE
blep-0.0.1.dist-info/METADATA
blep-0.0.1.dist-info/WHEEL
blep-0.0.1.dist-info/top_level.txt
blep-0.0.1.dist-info/RECORD
